{
  "recordings": [
    {
      "id": "1234",
      "title": "Paphos",
      "country": "Cyprus",
      "date": "2024-04-09T04:49:04.128Z",
      "description": "dfhdfh",
      "position": {
        "lat": "34.77094763658632",
        "lng": "32.41241455078126"
      }
    },
    {
      "id": "2222",
      "title": "Bournemouth",
      "country": "United Kingdom of Great Britain and Northern Ireland (the)",
      "date": "2024-04-11T00:05:33.223Z",
      "description": "",
      "position": {
        "lat": "50.71733015526967",
        "lng": "-1.8731689453125002"
      }
    },
    {
      "id": "90f1",
      "title": "",
      "locality": "Bellebrune",
      "country": "France",
      "date": "2024-07-27T21:00:10.579Z",
      "description": "",
      "position": {
        "lat": "50.73697118599811",
        "lng": "1.7914581298828127"
      }
    },
    {
      "id": "3c92",
      "title": "tester",
      "locality": "Bricquebec-en-Cotentin",
      "country": "France",
      "notes": "sdgsdg",
      "date": "2024-07-02T23:18:56.000Z"
    },
    {
      "id": "44d2",
      "title": "",
      "locality": "Jersey",
      "country": "Jersey",
      "notes": "",
      "date": "2024-07-29T23:21:26.835Z"
    },
    {
      "id": "6b6c",
      "title": "test",
      "locality": "Bricquebec-en-Cotentin",
      "country": "France",
      "notes": "testing",
      "date": "2024-07-02T02:02:37.000Z"
    },
    {
      "id": "ec3e",
      "title": "test",
      "locality": "Bricquebec-en-Cotentin",
      "country": "France",
      "lat": "49.45497940698962",
      "lng": "-1.728801727294922",
      "notes": "rest",
      "date": "2024-07-02T02:13:15.000Z",
      "position": {
        "lat": "49.45497940698962",
        "lng": "-1.728801727294922"
      }
    },
    {
      "id": "219e",
      "title": "best",
      "locality": "Bricquebec-en-Cotentin",
      "country": "France",
      "lat": "49.45497940698962",
      "lng": "-1.728801727294922",
      "notes": "rest",
      "date": "2024-07-02T02:13:15.000Z",
      "position": {
        "lat": "49.45497940698962",
        "lng": "-1.728801727294922"
      }
    }
  ]
}